opentelemetry/instrumentation/langchain_openai_embeddings/__init__.py
opentelemetry/instrumentation/langchain_openai_embeddings/async.json
opentelemetry/instrumentation/langchain_openai_embeddings/py.typed
opentelemetry/instrumentation/langchain_openai_embeddings/sync.json
opentelemetry_instrumentation_langchain_openai_embeddings-0.1.3.dist-info/METADATA
opentelemetry_instrumentation_langchain_openai_embeddings-0.1.3.dist-info/WHEEL
opentelemetry_instrumentation_langchain_openai_embeddings-0.1.3.dist-info/RECORD
