Metadata-Version: 2.4
Name: opentelemetry-instrumentation-langchain-openai-embeddings
Version: 0.1.3
Summary: OpenTelemetry langchain_openai.embeddings instrumentation
Author-email: Di-Is <rohoxbox@gmail.com>
License-Expression: Apache-2.0
Requires-Python: <3.14,>=3.9
Requires-Dist: langchain-openai>=0.3
Requires-Dist: opentelemetry-instrumentation
Requires-Dist: opentelemetry-sdk
Requires-Dist: opentelemetry-semantic-conventions-ai
Requires-Dist: wrapt
